{"GlobalPropertiesHash":"2ilJ2M8+ZdH0swl4cXFj9Ji8kay0R08ISE/fEc+OL0o=","FingerprintPatternsHash":"8ZRc1sGeVrPBx4lD717BgRaQekyh78QKV9SKsdt638U=","PropertyOverridesHash":"8ZRc1sGeVrPBx4lD717BgRaQekyh78QKV9SKsdt638U=","InputHashes":["XmSy3O59bBC1A8xCCKz0Tc7APyQeNLm1bXVLjdHnkUg="],"CachedAssets":{"XmSy3O59bBC1A8xCCKz0Tc7APyQeNLm1bXVLjdHnkUg=":{"Identity":"C:\\Users\\perte\\OneDrive\\Desktop\\WhistleblowingApp\\obj\\Debug\\net9.0\\compressed\\6jlcitkszu-3wkcksydui.gz","SourceId":"WhistleblowingApp","SourceType":"Discovered","ContentRoot":"C:\\Users\\perte\\OneDrive\\Desktop\\WhistleblowingApp\\obj\\Debug\\net9.0\\compressed\\","BasePath":"_content/WhistleblowingApp","RelativePath":"css/site#[.{fingerprint=3wkcksydui}]?.css.gz","AssetKind":"All","AssetMode":"All","AssetRole":"Alternative","AssetMergeBehavior":null,"AssetMergeSource":"","RelatedAsset":"C:\\Users\\perte\\OneDrive\\Desktop\\WhistleblowingApp\\wwwroot\\css\\site.css","AssetTraitName":"Content-Encoding","AssetTraitValue":"gzip","Fingerprint":"kg3ku6z9tm","Integrity":"hHRzE/zexN8goxOX3XA0OU1EpKsHymy/cwlEole0kSI=","CopyToOutputDirectory":"Never","CopyToPublishDirectory":"PreserveNewest","OriginalItemSpec":"C:\\Users\\perte\\OneDrive\\Desktop\\WhistleblowingApp\\wwwroot\\css\\site.css","FileLength":3418,"LastWriteTime":"2025-07-07T17:15:49.2700017+00:00"}},"CachedCopyCandidates":{}}